__init__.py
mlinfra/README.md
mlinfra/__init__.py
mlinfra/amplitude.py
mlinfra/cli/__init__.py
mlinfra/cli/cli.py
mlinfra/cli/terraform.py
mlinfra/cli/utilities.py
mlinfra/enums/__init__.py
mlinfra/enums/cloud_provider.py
mlinfra/enums/deployment_type.py
mlinfra/modules/__init__.py
mlinfra/modules/applications/README.md
mlinfra/modules/applications/cloud_vm/data_versioning/lakefs/README.md
mlinfra/modules/applications/cloud_vm/data_versioning/lakefs/lakefs_cloud_vm.yaml
mlinfra/modules/applications/cloud_vm/data_versioning/lakefs/tf_module/lakefs-dynamodb-config.tpl
mlinfra/modules/applications/cloud_vm/data_versioning/lakefs/tf_module/lakefs-postgres-config.tpl
mlinfra/modules/applications/cloud_vm/data_versioning/lakefs/tf_module/main.tf
mlinfra/modules/applications/cloud_vm/data_versioning/lakefs/tf_module/outputs.tf
mlinfra/modules/applications/cloud_vm/data_versioning/lakefs/tf_module/remote-cloud-init.tpl
mlinfra/modules/applications/cloud_vm/data_versioning/lakefs/tf_module/simple-cloud-init.tpl
mlinfra/modules/applications/cloud_vm/data_versioning/lakefs/tf_module/variables.tf
mlinfra/modules/applications/cloud_vm/experiment_tracking/mlflow/README.md
mlinfra/modules/applications/cloud_vm/experiment_tracking/mlflow/mlflow_cloud_vm.yaml
mlinfra/modules/applications/cloud_vm/experiment_tracking/mlflow/tf_module/main.tf
mlinfra/modules/applications/cloud_vm/experiment_tracking/mlflow/tf_module/outputs.tf
mlinfra/modules/applications/cloud_vm/experiment_tracking/mlflow/tf_module/remote-cloud-init.tpl
mlinfra/modules/applications/cloud_vm/experiment_tracking/mlflow/tf_module/simple-cloud-init.tpl
mlinfra/modules/applications/cloud_vm/experiment_tracking/mlflow/tf_module/variables.tf
mlinfra/modules/applications/cloud_vm/experiment_tracking/wandb/wandb_cloud_vm.yaml
mlinfra/modules/applications/cloud_vm/experiment_tracking/wandb/tf_module/main.tf
mlinfra/modules/applications/cloud_vm/experiment_tracking/wandb/tf_module/outputs.tf
mlinfra-0.0.29.dist-info/licenses/LICENSE
mlinfra-0.0.29.dist-info/licenses/LICENSE_HEADER.txt
mlinfra-0.0.29.dist-info/METADATA
mlinfra-0.0.29.dist-info/WHEEL
mlinfra-0.0.29.dist-info/entry_points.txt
mlinfra-0.0.29.dist-info/top_level.txt
mlinfra-0.0.29.dist-info/RECORD
