Metadata-Version: 2.4
Name: mlinfra
Version: 0.0.29
Summary: A tool to deploy mlops tooling at the click of a button.
Author-email: Ali Abbas Jaffri <ali.abbasjaffri@live.com>
Maintainer-email: Ali Abbas Jaffri <ali.abbasjaffri@live.com>
License:                                  Apache License
Project-URL: Homepage, https://github.com/mlinfra-io/mlinfra
Project-URL: Repository, https://github.com/mlinfra-io/mlinfra.git
Project-URL: Documentation, https://mlinfra.io/
Keywords: mlinfra
Classifier: Development Status :: 3 - Alpha
Classifier: Intended Audience :: Developers
Classifier: Intended Audience :: Science/Research
Classifier: License :: OSI Approved :: Apache Software License
Classifier: Operating System :: OS Independent
Classifier: Programming Language :: Python :: 3
Classifier: Topic :: Scientific/Engineering
Classifier: Topic :: Scientific/Engineering :: Artificial Intelligence
Classifier: Topic :: Software Development
Classifier: Topic :: Software Development :: Libraries :: Python Modules
Classifier: Topic :: Utilities
Classifier: Topic :: System :: Distributed Computing
Requires-Python: >=3.11
License-File: LICENSE
License-File: LICENSE_HEADER.txt
Requires-Dist: boto3
Requires-Dist: pyyaml
Requires-Dist: GitPython
Requires-Dist: mypy
Requires-Dist: getmac
Requires-Dist: requests
Requires-Dist: typer
Requires-Dist: rich
Provides-Extra: dev
Requires-Dist: pre-commit; extra == "dev"
Requires-Dist: pytest; extra == "dev"
Requires-Dist: pytest-mock; extra == "dev"
Requires-Dist: zipp>=3.20.2; extra == "dev"
Provides-Extra: docs
Requires-Dist: mkdocs-material; extra == "docs"
Requires-Dist: mkdocs-git-revision-date-localized-plugin; extra == "docs"
Requires-Dist: mike; extra == "docs"
Requires-Dist: mkdocs-section-index; extra == "docs"
Dynamic: license-file
